{"nodes": [{"id": "emd_validate_emd_fn", "label": "validate_emd() function", "file_type": "code", "source_file": "src/checkers/emd_validator.py", "source_location": "L14-L95", "source_url": null, "captured_at": null, "author": null, "contributor": null}, {"id": "emd_rules_constants", "label": "EMD rules: 2% of NIT + 45-day validity", "file_type": "code", "source_file": "src/checkers/emd_validator.py", "source_location": "docstring", "source_url": null, "captured_at": null, "author": null, "contributor": null}], "edges": [{"source": "emd_validate_emd_fn", "target": "settings_emd_params", "relation": "shares_data_with", "confidence": "EXTRACTED", "confidence_score": 1.0, "source_file": "src/checkers/emd_validator.py", "source_location": "L36,L53,L66,L75", "weight": 1.0}, {"source": "emd_validate_emd_fn", "target": "settings_get_settings_fn", "relation": "calls", "confidence": "EXTRACTED", "confidence_score": 1.0, "source_file": "src/checkers/emd_validator.py", "source_location": "L36", "weight": 1.0}, {"source": "emd_rules_constants", "target": "theme_nonnegotiables", "relation": "rationale_for", "confidence": "INFERRED", "confidence_score": 0.7, "source_file": "src/checkers/emd_validator.py", "source_location": "docstring", "weight": 1.0}, {"source": "emd_validate_emd_fn", "target": "ruleengine_evaluate_fn", "relation": "semantically_similar_to", "confidence": "INFERRED", "confidence_score": 0.75, "source_file": "src/checkers/emd_validator.py", "source_location": "entire", "weight": 1.0}], "hyperedges": []}